{
  "id": "9b82e9ba-1e97-4876-884c-b709d21a20ae",
  "name": "task-ESE-16-1",
  "type": "task",
  "title": "Install Storybook and configure for the project",
  "stub": "install-storybook-and-configure-for-the-project",
  "tree": [16, 1],
  "status": "inRefinement",
  "description": "",
  "acceptanceCriteria": "",
  "demoDeliverable": "",
  "testingScenarios": "",
  "testingNotes": "",
  "size": null,
  "sizeLabel": null,
  "subtasks": [],
  "stakeholderUnderstanding": "",
  "demoAccepted": false,
  "team": "",
  "started": null,
  "completed": null,
  "blockers": "",
  "knowledgeGaps": "",
  "comments": "",
  "parentName": "task-ESE-16",
  "sprintName": null
}
